icrn/__init__.py
icrn/dict_utils.py
icrn/numerics.py
icrn/representation.py
icrn/simulator.py
icrn/test_dict_utils.py
icrn/test_end_to_end.py
icrn/test_numerics.py
icrn/test_representation.py
icrn/test_simulator.py
icrn-0.1.0.dist-info/METADATA
icrn-0.1.0.dist-info/WHEEL
icrn-0.1.0.dist-info/licenses/LICENSE
icrn-0.1.0.dist-info/RECORD
