Metadata-Version: 2.4
Name: icrn
Version: 0.1.0
Summary: Indexed Chemical Reaction Networks in a differentiable, tensor-based framework
Project-URL: Homepage, https://github.com/SwissChardLeaf/icrn
Project-URL: Issues, https://github.com/SwissChardLeaf/icrn/issues
Author-email: Inhoo Lee <research22426@gmail.com>
License-Expression: MIT
License-File: LICENSE
Classifier: Operating System :: OS Independent
Classifier: Programming Language :: Python :: 3
Requires-Python: >=3.9
